culminator/__init__.py
culminator/classif.py
culminator/classification.py
culminator/clus.py
culminator/clustering.py
culminator/reg.py
culminator/regression.py
culminator-0.16.dist-info/METADATA
culminator-0.16.dist-info/WHEEL
culminator-0.16.dist-info/top_level.txt
culminator-0.16.dist-info/RECORD
