Metadata-Version: 2.1
Name: culminator
Version: 0.16
Requires-Dist: numpy
Requires-Dist: pandas
